svc_user_auth_zxw/__init__.py
svc_user_auth_zxw/config.py
svc_user_auth_zxw/main.py
svc_user_auth_zxw/会员管理页面.html
svc_user_auth_zxw/SDK_jwt/__init__.py
svc_user_auth_zxw/SDK_jwt/demo.py
svc_user_auth_zxw/SDK_jwt/jwt.py
svc_user_auth_zxw/SDK_jwt/jwt_刷新管理.py
svc_user_auth_zxw/SDK_jwt/apis/__init__.py
svc_user_auth_zxw/SDK_jwt/apis/api_刷新token.py
svc_user_auth_zxw/SDK_jwt/db_model/__init__.py
svc_user_auth_zxw/SDK_jwt/db_model/model.py
svc_user_auth_zxw/apis/__init__.py
svc_user_auth_zxw/apis/api_JWT.py
svc_user_auth_zxw/apis/api_会员权限验证.py
svc_user_auth_zxw/apis/api_会员类型管理.py
svc_user_auth_zxw/apis/api_用户会员管理.py
svc_user_auth_zxw/apis/api_用户权限_增加.py
svc_user_auth_zxw/apis/api_用户权限_验证.py
svc_user_auth_zxw/apis/api_邀请管理.py
svc_user_auth_zxw/apis/schemas.py
svc_user_auth_zxw/apis/api_登录注册/__init__.py
svc_user_auth_zxw/apis/api_登录注册/func_获取邀请码.py
svc_user_auth_zxw/apis/api_登录注册/login.py
svc_user_auth_zxw/apis/api_登录注册/logout.py
svc_user_auth_zxw/apis/api_登录注册/微信H5快捷登录/__init__.py
svc_user_auth_zxw/apis/api_登录注册/微信H5快捷登录/api_注册登录.py
svc_user_auth_zxw/apis/api_登录注册/手机注册登录/__init__.py
svc_user_auth_zxw/apis/api_登录注册/手机注册登录/api_手机号管理.py
svc_user_auth_zxw/apis/api_登录注册/手机注册登录/api_注册登录.py
svc_user_auth_zxw/apis/api_登录注册/手机注册登录/测试短信验证码.py
svc_user_auth_zxw/apis/api_登录注册/账号密码注册登录/__init__.py
svc_user_auth_zxw/apis/api_登录注册/账号密码注册登录/api_注册登录.py
svc_user_auth_zxw/db/__init__.py
svc_user_auth_zxw/db/crud2_会员表.py
svc_user_auth_zxw/db/get_db.py
svc_user_auth_zxw/db/models.py
svc_user_auth_zxw/db/编码参考crud0_applications.py
svc_user_auth_zxw/interface/__init__.py
svc_user_auth_zxw/interface/invitation_interface.py
svc_user_auth_zxw/tests/__init__.py
svc_user_auth_zxw/tests/test_apis.py
svc_user_auth_zxw/tests/test_会员功能.py
svc_user_auth_zxw/tests/test_权限.py
svc_user_auth_zxw/tools/__init__.py
svc_user_auth_zxw/tools/check_sms_code.py
svc_user_auth_zxw/tools/error_code.py
svc_user_auth_zxw/tools/func_用户id加密.py
svc_user_auth_zxw/tools/http_exception.py
svc_user_auth_zxw-3.3.9.dist-info/METADATA
svc_user_auth_zxw-3.3.9.dist-info/WHEEL
svc_user_auth_zxw-3.3.9.dist-info/top_level.txt
svc_user_auth_zxw-3.3.9.dist-info/RECORD
