Metadata-Version: 2.4
Name: svc_user_auth_zxw
Version: 3.3.9
Summary: 用户权限验证工具包
Home-page: https://github.com/sunshineinwater/
Author: 景募
Author-email: 
Classifier: Programming Language :: Python :: 3.10
Classifier: License :: OSI Approved :: MIT License
Classifier: Operating System :: OS Independent
Requires-Dist: pycryptodome<=3.22.0,>=3.20.0
Requires-Dist: fastapi<0.113,>=0.112.0
Requires-Dist: jose<1.1.0,>=1.0.0
Requires-Dist: aiohttp>=3.12.14
Requires-Dist: httpx>=0.28.1
Requires-Dist: sqlalchemy==2.0.32
Requires-Dist: greenlet==3.0.3
Requires-Dist: databases==0.9.0
Requires-Dist: python-jose>=3.4.0
Requires-Dist: passlib==1.7.4
Requires-Dist: bcrypt==4.2.0
Requires-Dist: asyncpg==0.29.0
Requires-Dist: uvicorn<0.31.0,>=0.30.0
Requires-Dist: python-multipart>=0.0.19
Requires-Dist: app-tools-zxw>=2.2.1
Requires-Dist: alibabacloud_dysmsapi20170525==3.0.0
Requires-Dist: redis==5.2.0
Requires-Dist: apscheduler==3.10.4
Dynamic: author
Dynamic: classifier
Dynamic: description
Dynamic: description-content-type
Dynamic: home-page
Dynamic: requires-dist
Dynamic: summary
